Ntldz/__init__.py
Ntldz/solver.py
ntldz-0.1.0.dist-info/licenses/LICENSE
ntldz-0.1.0.dist-info/METADATA
ntldz-0.1.0.dist-info/WHEEL
ntldz-0.1.0.dist-info/top_level.txt
ntldz-0.1.0.dist-info/RECORD
