Metadata-Version: 2.4
Name: Ntldz
Version: 0.1.0
Summary: Một công cụ tuyệt vời cho những thằng cụt tay và thiểu năng
Home-page: https://facebook.com/ntldev1507
Author: Ntl
Author-email: nhuthanhlong89@gmail.com
License: MIT
Classifier: Programming Language :: Python :: 3
Classifier: License :: OSI Approved :: MIT License
Classifier: Operating System :: OS Independent
Requires-Python: >=3.7
License-File: LICENSE
Requires-Dist: DrissionPage>=4.1.0.18
Requires-Dist: pydub>=0.25.1
Requires-Dist: SpeechRecognition>=3.14.3
Dynamic: license-file
Dynamic: requires-dist
